{
  "background": "img/electrobudka.jpg",
  "music": "sound/night_theme.ogg",
  "bgcolor": "rgb(0, 0, 0)",
  "cursor": "url(img/cursor_night.png)",
  "invertText": true,
  "spotlight": "transparent 0%, rgba(220, 195, 100, 0.7) 1%, rgba(220, 185, 70, 0.4) 1.2%, rgba(225, 220, 95, 0.2) 1.4%, transparent 8%, rgba(0, 0, 0, 0.6) 35%",
  "text": "<div class='textblock' style='text-align: center; width: 413px; height: 310px; margin-left: 545px; margin-top: 242px;'>\t<div class='block' id='1'>\n\t  Я ринулся вперёд. Чудом удалось мне попасть в дом раньше, чем неведомый преследователь настиг меня.</br><a href=# class='link' id='dom_from_kolodetz_3doors'>Захлопнуть дверь</a></div></div>"
}